py_ad_principal/__init__.py
py_ad_principal/py_ad_principal.py
py_ad_principal-0.2.2.dist-info/WHEEL
py_ad_principal-0.2.2.dist-info/METADATA
py_ad_principal-0.2.2.dist-info/RECORD
