Metadata-Version: 2.3
Name: py_ad_principal
Version: 0.2.2
Summary: A Python package for authenticating users (more formally called principals) via a Microsoft Active Directory (AD) domain controller.
Keywords: active directory,authentication,principal,user,ldap,kerberos,sso,microsoft,active directory,gssapi
Author: Jason Hallford
Requires-Python: >=3.11
Classifier: Programming Language :: Python :: 3
Classifier: License :: OSI Approved :: MIT License
Classifier: Operating System :: POSIX :: Linux
Requires-Dist: gssapi >= 1.9.0
Requires-Dist: ldap3 >= 2.9.1
Project-URL: Homepage, https://github.com/miscellanea-io/py-ad-principal
Project-URL: Issues, https://github.com/miscellanea-io/py-ad-principal/issues
